ddc_utility/__init__.py
ddc_utility/auth.py
ddc_utility/client.py
ddc_utility/constants.py
ddc_utility/cube.py
ddc_utility/errors.py
ddc_utility/logger.py
ddc_utility/utils.py
ddc_utility-1.8.0.dist-info/licenses/LICENSE
ddc_utility-1.8.0.dist-info/METADATA
ddc_utility-1.8.0.dist-info/WHEEL
ddc_utility-1.8.0.dist-info/top_level.txt
ddc_utility-1.8.0.dist-info/RECORD
