Metadata-Version: 2.4
Name: ddc-utility
Version: 1.8.0
Summary: Client package for the DDC API.
Author-email: Balint Alfoldy <balint.alfoldy@cropom.com>, Peter Hazi <peter.hazi@cropom.com>, Marton Tolnai <marton.tolnai@cropom.com>
License: The MIT License (MIT)
Classifier: Programming Language :: Python :: 3
Classifier: License :: OSI Approved :: MIT License
Classifier: Operating System :: OS Independent
Requires-Python: >=3.10
License-File: LICENSE
Requires-Dist: dask>=2023.1.1
Requires-Dist: Jinja2>=3.1.2
Requires-Dist: matplotlib>=3.6.2
Requires-Dist: numcodecs>=0.11.0
Requires-Dist: pyproj>=3.4.1
Requires-Dist: requests>=2.28.2
Requires-Dist: xarray>=2023.1.0
Requires-Dist: zarr>=2.13.6
Requires-Dist: fsspec
Requires-Dist: s3fs
Requires-Dist: shapely
Requires-Dist: pydantic>=2.8.0
Dynamic: license-file
